gnomock/__init__.py
gnomock/api_client.py
gnomock/configuration.py
gnomock/exceptions.py
gnomock/rest.py
gnomock/api/__init__.py
gnomock/api/presets_api.py
gnomock/models/__init__.py
gnomock/models/cassandra.py
gnomock/models/cassandra_request.py
gnomock/models/cockroachdb.py
gnomock/models/cockroachdb_request.py
gnomock/models/container.py
gnomock/models/elastic.py
gnomock/models/elastic_request.py
gnomock/models/influxdb.py
gnomock/models/influxdb_request.py
gnomock/models/invalid_start_request.py
gnomock/models/invalid_stop_request.py
gnomock/models/kafka.py
gnomock/models/kafka_messages.py
gnomock/models/kafka_request.py
gnomock/models/kubernetes.py
gnomock/models/kubernetes_request.py
gnomock/models/localstack.py
gnomock/models/localstack_request.py
gnomock/models/mariadb.py
gnomock/models/mariadb_request.py
gnomock/models/memcached.py
gnomock/models/memcached_request.py
gnomock/models/mongo.py
gnomock/models/mongo_request.py
gnomock/models/mssql.py
gnomock/models/mssql_request.py
gnomock/models/mysql.py
gnomock/models/mysql_request.py
gnomock/models/options.py
gnomock/models/postgres.py
gnomock/models/postgres_request.py
gnomock/models/rabbitmq.py
gnomock/models/rabbitmq_message.py
gnomock/models/rabbitmq_request.py
gnomock/models/redis.py
gnomock/models/redis_request.py
gnomock/models/splunk.py
gnomock/models/splunk_request.py
gnomock/models/splunk_values.py
gnomock/models/start_failed.py
gnomock/models/stop_failed.py
gnomock/models/stop_request.py
gnomock/test/__init__.py
gnomock/test/test_container.py
gnomock/test/test_invalid_start_request.py
gnomock/test/test_invalid_stop_request.py
gnomock/test/test_localstack.py
gnomock/test/test_localstack_request.py
gnomock/test/test_mongo.py
gnomock/test/test_mongo_request.py
gnomock/test/test_mssql.py
gnomock/test/test_mssql_request.py
gnomock/test/test_mysql.py
gnomock/test/test_mysql_request.py
gnomock/test/test_options.py
gnomock/test/test_postgres.py
gnomock/test/test_postgres_request.py
gnomock_python_sdk-1.19.0.dist-info/METADATA
gnomock_python_sdk-1.19.0.dist-info/WHEEL
gnomock_python_sdk-1.19.0.dist-info/top_level.txt
gnomock_python_sdk-1.19.0.dist-info/RECORD
