Metadata-Version: 2.1
Name: gnomock-python-sdk
Version: 1.19.0
Summary: gnomock
Home-page: UNKNOWN
Author: OpenAPI Generator community
Author-email: team@openapitools.org
License: MIT
Keywords: OpenAPI,OpenAPI-Generator,gnomock
Platform: UNKNOWN
Requires-Dist: urllib3 (>=1.15)
Requires-Dist: six (>=1.10)
Requires-Dist: certifi
Requires-Dist: python-dateutil
